[
    {
        "nome": "Boina de Espuma Flat Azul Refino Lustro Sem Interface  5,5\" Lincoln",
        "descricao": "Seu conceito é moderno, eficiente e econômico sem perder a máxima qualidade, que é a característica dos produtos Lincoln Polidores.",
        "preco": "R$ 56,90",
        "imagem": "https://images.tcdn.com.br/files/606785/themes/95/img/settings/casa.png?8d0a93ae6301f11fb3959efd9fc0d673",
        "link": "https://www.artwax.com.br/polimento/boinas/boina-refino/boina-de-espuma-flat-azul-5-5-refino-lincoln",
        "marca": "Lincoln",
        "fispq": null
    },
    {
        "nome": "Boina de Espuma Flat Corte Leve Refino 5,5\" Sem Interface Lincoln",
        "descricao": "Seu conceito é moderno, eficiente e econômico sem perder a máxima qualidade, que é a característica dos produtos Lincoln Polidores",
        "preco": "R$ 56,90",
        "imagem": "https://images.tcdn.com.br/files/606785/themes/95/img/settings/casa.png?8d0a93ae6301f11fb3959efd9fc0d673",
        "link": "https://www.artwax.com.br/polimento/boinas/boina-corte/boina-de-espuma-flat-laranja-5-5-corte-lincoln",
        "marca": "Lincoln",
        "fispq": null
    },
    {
        "nome": "Boina Voxer Corte Médio 3\" Espuma Azul Escura Vonixx",
        "descricao": "Desenvolvido para remoção de defeitos moderados. Proporciona um excelente nível de acabamento. É indicada também para ser utilizada com produtos one step.",
        "preco": "R$ 42,90",
        "imagem": "https://images.tcdn.com.br/files/606785/themes/95/img/settings/casa.png?8d0a93ae6301f11fb3959efd9fc0d673",
        "link": "https://www.artwax.com.br/marcas/vonixx/boina-voxer-corte-medio-3-espuma-azul-escura-vonixx",
        "marca": "Vonixx",
        "fispq": null
    },
    {
        "nome": "Boina Voxer Corte Médio 5\" Espuma Azul Escura Vonixx",
        "descricao": "Desenvolvido para remoção de defeitos moderados. Proporciona um excelente nível de acabamento. É indicada também para ser utilizada com produtos one step.",
        "preco": "R$ 62,90",
        "imagem": "https://images.tcdn.com.br/files/606785/themes/95/img/settings/casa.png?8d0a93ae6301f11fb3959efd9fc0d673",
        "link": "https://www.artwax.com.br/marcas/boina-voxer-corte-medio-5-espuma-azul-escura-vonixx",
        "marca": "Vonixx",
        "fispq": null
    },
    {
        "nome": "Boina Voxer Corte Médio 6\" Espuma Azul Escura Vonixx",
        "descricao": "Desenvolvido para remoção de defeitos moderados. Proporciona um excelente nível de acabamento. É indicada também para ser utilizada com produtos one step.",
        "preco": "R$ 68,90",
        "imagem": "https://images.tcdn.com.br/files/606785/themes/95/img/settings/casa.png?8d0a93ae6301f11fb3959efd9fc0d673",
        "link": "https://www.artwax.com.br/marcas/boina-voxer-corte-medio-6-espuma-azul-escura-vonixx",
        "marca": "Vonixx",
        "fispq": null
    },
    {
        "nome": "Boina de lã Híbrida Corte 6\" Sem Interface For Detail",
        "descricao": "A Boina De Lã Híbrida 6? Para Corte For Detail é o acessório ideal para detalhadores que buscam um corte agressivo e eficiente em seus projetos de polimento. Compatível com diversos produtos e diferentes compostos de polimento.",
        "preco": "R$ 54,90",
        "imagem": "https://images.tcdn.com.br/files/606785/themes/95/img/settings/casa.png?8d0a93ae6301f11fb3959efd9fc0d673",
        "link": "https://www.artwax.com.br/polimento/boinas/boina-corte/boina-de-la-hibrida-mista-branca-corte-para-roto-orbital-6-for-detail",
        "marca": "FOR DETAIL",
        "fispq": null
    },
    {
        "nome": "Boina de Espuma Hyper Verde Corte 6\" Sem Interface Kers",
        "descricao": "As boinas de espuma para polimento Hyper possui cortes hexagonais por sua base, esses cortes permitem a melhor performance na hora do polimento, melhoram o fluxo de ar pela boina, evitando o aquecimento, permitem uma distribuição uniforme do produto e reté",
        "preco": "R$ 83,90",
        "imagem": "https://images.tcdn.com.br/files/606785/themes/95/img/settings/casa.png?8d0a93ae6301f11fb3959efd9fc0d673",
        "link": "https://www.artwax.com.br/polimento/boinas/boina-corte/boina-de-espuma-hyper-verde-corte-6-sem-interface-kers",
        "marca": "Kers",
        "fispq": null
    },
    {
        "nome": "Boina de Espuma Hyper Azul Lustro 6\" Sem Interface Kers",
        "descricao": "-",
        "preco": "R$ 66,90",
        "imagem": "https://images.tcdn.com.br/files/606785/themes/95/img/settings/casa.png?8d0a93ae6301f11fb3959efd9fc0d673",
        "link": "https://www.artwax.com.br/uso-externo/boina-de-espuma-lustro-hyper-6-sem-interface-kers",
        "marca": "Kers",
        "fispq": null
    },
    {
        "nome": "Boina de Espuma Hyper Laranja Média Refino 6\" Sem Interface Kers",
        "descricao": "-",
        "preco": "R$ 66,90",
        "imagem": "https://images.tcdn.com.br/files/606785/themes/95/img/settings/casa.png?8d0a93ae6301f11fb3959efd9fc0d673",
        "link": "https://www.artwax.com.br/polimento/boinas/boina-refino/boina-de-espuma-hyper-laranja-media-refino-6-sem-interface-kers",
        "marca": "Kers",
        "fispq": null
    },
    {
        "nome": "Boina Jeans Hard Cut Corte Pesado 6\" Com Interface Detailer",
        "descricao": "Indicada para uso com máquina Roto-Orbital para remover",
        "preco": "R$ 46,90",
        "imagem": "https://images.tcdn.com.br/files/606785/themes/95/img/settings/casa.png?8d0a93ae6301f11fb3959efd9fc0d673",
        "link": "https://www.artwax.com.br/polimento/boinas/boina-corte/boina-jeans-hard-cut-corte-pesado-6-detailer",
        "marca": "Detailer",
        "fispq": null
    },
    {
        "nome": "Boina Jeans Hard Cut Corte Pesado 3\" Com Interface Detailer",
        "descricao": "Indicada para uso com máquina Roto-Orbital para remover",
        "preco": "R$ 32,90",
        "imagem": "https://images.tcdn.com.br/files/606785/themes/95/img/settings/casa.png?8d0a93ae6301f11fb3959efd9fc0d673",
        "link": "https://www.artwax.com.br/polimento/boinas/boina-corte/boina-jeans-hard-cut-corte-pesado-3-detailer",
        "marca": "Detailer",
        "fispq": null
    },
    {
        "nome": "Boinas Jeans Hard Cut Corte Pesado 3\" e 6\" Detailer Kit  2 Unidades",
        "descricao": "Indicada para uso com máquina Roto-Orbital para remover",
        "preco": "R$ 92,80",
        "imagem": "https://images.tcdn.com.br/files/606785/themes/95/img/settings/casa.png?8d0a93ae6301f11fb3959efd9fc0d673",
        "link": "https://www.artwax.com.br/kits/kit-boinas-jeans-hard-cut-corte-pesado-detailer-3-e-6",
        "marca": "Detailer",
        "fispq": null
    },
    {
        "nome": "Boina de Algodão Agressiva 5\" Para Polimento De Vidros Mills",
        "descricao": "-",
        "preco": "R$ 50,00",
        "imagem": "https://images.tcdn.com.br/files/606785/themes/95/img/settings/casa.png?8d0a93ae6301f11fb3959efd9fc0d673",
        "link": "https://www.artwax.com.br/polimento/boina-de-algodao-agressiva-5-para-polimento-de-vidros-mills",
        "marca": "Mills",
        "fispq": null
    },
    {
        "nome": "Boina de Algodão Agressiva 3\" Para Polimento De Vidros Mills",
        "descricao": "-",
        "preco": "R$ 33,00",
        "imagem": "https://images.tcdn.com.br/files/606785/themes/95/img/settings/casa.png?8d0a93ae6301f11fb3959efd9fc0d673",
        "link": "https://www.artwax.com.br/boina-de-algodao-agressiva-3",
        "marca": "Mills",
        "fispq": null
    },
    {
        "nome": "Boina de Lã Hibrida Corte 3\" Sem Interface Artwax",
        "descricao": "boina Hibrida utiliza fio de lã natural com 20 % de poliéster. Essa mistura produz um corte potente aliado a baixas marcações de holografia na peça, facilitando as etapas de refino e acabamento.\r\nCaso você deseje um corte um pouco mais leve, basta adiciona",
        "preco": "R$ 28,90",
        "imagem": "https://images.tcdn.com.br/files/606785/themes/95/img/settings/casa.png?8d0a93ae6301f11fb3959efd9fc0d673",
        "link": "https://www.artwax.com.br/polimento/boinas/boina-corte/boina-de-la-hibrida-corte-3-sem-interface-artwax",
        "marca": "Artwax",
        "fispq": null
    },
    {
        "nome": "Boina de Feltro Para Polimento de Vidros 5\" Dune Glass  Alcance",
        "descricao": "A boina DUNE GLASS é composta de lã compactada 100% natural fina e densa, capaz de suportar altas temperaturas e níveis de atrito.",
        "preco": "R$ 49,90",
        "imagem": "https://images.tcdn.com.br/files/606785/themes/95/img/settings/casa.png?8d0a93ae6301f11fb3959efd9fc0d673",
        "link": "https://www.artwax.com.br/uso-externo/vidros/alcance-dune-glass-5-boina-de-feltro-para-polimento-de-vidros",
        "marca": "Alcance",
        "fispq": null
    },
    {
        "nome": "Boina de Espuma Hyper Azul Lustro 5\" Kers",
        "descricao": "As boinas de espuma para polimento Hyper possui cortes hexagonais por sua base, esses cortes permitem a melhor performance na hora do polimento",
        "preco": "R$ 66,90",
        "imagem": "https://images.tcdn.com.br/files/606785/themes/95/img/settings/casa.png?8d0a93ae6301f11fb3959efd9fc0d673",
        "link": "https://www.artwax.com.br/polimento/boinas/boina-lustro/kers-boina-de-espuma-hyper-5-azul-suave-lustro",
        "marca": "Kers",
        "fispq": null
    },
    {
        "nome": "Boina de Espuma Hyper 5\" Verde Agressiva Corte Kers",
        "descricao": "As boinas de espuma para polimento Hyper possui cortes hexagonais por sua base, esses cortes permitem a melhor performance na hora do polimento, melhoram o fluxo de ar pela boina.",
        "preco": "R$ 66,90",
        "imagem": "https://images.tcdn.com.br/files/606785/themes/95/img/settings/casa.png?8d0a93ae6301f11fb3959efd9fc0d673",
        "link": "https://www.artwax.com.br/polimento/boinas/boina-corte/kers-boina-de-espuma-hyper-5-verde-agressiva-corte",
        "marca": "Kers",
        "fispq": null
    },
    {
        "nome": "Boina de Espuma Laranja Hyper Corte Refino Média 5\" Kers",
        "descricao": "As boinas de espuma para polimento Hyper possui cortes hexagonais por sua base, esses cortes permitem a melhor performance na hora do polimento",
        "preco": "R$ 66,90",
        "imagem": "https://images.tcdn.com.br/files/606785/themes/95/img/settings/casa.png?8d0a93ae6301f11fb3959efd9fc0d673",
        "link": "https://www.artwax.com.br/polimento/boinas/boina-corte/kers-boina-de-espuma-hyper-5-laranja-media-corterefino",
        "marca": "Kers",
        "fispq": null
    },
    {
        "nome": "Carpro CoolPad 5\" Boina Hibrida de Lã e Microfibra - 1un",
        "descricao": "O Coolpad é um híbrido de lã de carneiro e microfibra com design patenteado.",
        "preco": "R$ 199,02",
        "imagem": "https://images.tcdn.com.br/files/606785/themes/95/img/settings/casa.png?8d0a93ae6301f11fb3959efd9fc0d673",
        "link": "https://www.artwax.com.br/marcas/carpro-coolpad-5-boina-hibrida-de-la-e-microfibra",
        "marca": "Carpro",
        "fispq": null
    },
    {
        "nome": "Carpro CoolPad 3\" Boina Hibrida de Lã e Microfibra - 1un",
        "descricao": "O Coolpad é um híbrido de lã de carneiro e microfibra com design patenteado.",
        "preco": "R$ 99,66",
        "imagem": "https://images.tcdn.com.br/files/606785/themes/95/img/settings/casa.png?8d0a93ae6301f11fb3959efd9fc0d673",
        "link": "https://www.artwax.com.br/marcas/carpro-coolpad-3-boina-hibrida-de-la-e-microfibra",
        "marca": "Carpro",
        "fispq": null
    },
    {
        "nome": "Boina Voxer Corte Pesado 3\" Lã Vonixx",
        "descricao": "Desenvolvido para todos os tipos de vernizes, remove casca de laranja, defeitos severos e marcas de lixa 1200",
        "preco": "R$ 39,90",
        "imagem": "https://images.tcdn.com.br/files/606785/themes/95/img/settings/casa.png?8d0a93ae6301f11fb3959efd9fc0d673",
        "link": "https://www.artwax.com.br/marcas/boina-voxer-corte-pesado-3-la-vonixx",
        "marca": "Vonixx",
        "fispq": null
    },
    {
        "nome": "Boina Voxer Corte Pesado 5\" Lã Vonixx",
        "descricao": "Desenvolvido para todos os tipos de vernizes, remove casca de laranja, defeitos severos e marcas de lixa 1200.",
        "preco": "R$ 66,90",
        "imagem": "https://images.tcdn.com.br/files/606785/themes/95/img/settings/casa.png?8d0a93ae6301f11fb3959efd9fc0d673",
        "link": "https://www.artwax.com.br/marcas/boina-voxer-corte-pesado-5-la-vonixx",
        "marca": "Vonixx",
        "fispq": null
    },
    {
        "nome": "Boina Voxer Corte Pesado 6\" Lã Vonixx",
        "descricao": "Desenvolvido para todos os tipos de vernizes, remove casca de laranja, defeitos severos e marcas de lixa 1200.",
        "preco": "R$ 71,90",
        "imagem": "https://images.tcdn.com.br/files/606785/themes/95/img/settings/casa.png?8d0a93ae6301f11fb3959efd9fc0d673",
        "link": "https://www.artwax.com.br/marcas/boina-voxer-corte-pesado-6-la-vonixx",
        "marca": "Vonixx",
        "fispq": null
    },
    {
        "nome": "Boina de Microfibra Corte Com Interface Detailer 6,5\" Com Velcro",
        "descricao": "Boina Microfibra Com Interface",
        "preco": "R$ 59,90",
        "imagem": "https://images.tcdn.com.br/files/606785/themes/95/img/settings/casa.png?8d0a93ae6301f11fb3959efd9fc0d673",
        "link": "https://www.artwax.com.br/marcas/boina-de-microfibra-corte-com-interface-detailer-6-5-com-velcro",
        "marca": "Detailer",
        "fispq": null
    },
    {
        "nome": "Boina de Microfibra Corte Com Interface Detailer 3,5\" Com velcro",
        "descricao": "Boina Microfibra Com Interface",
        "preco": "R$ 39,90",
        "imagem": "https://images.tcdn.com.br/files/606785/themes/95/img/settings/casa.png?8d0a93ae6301f11fb3959efd9fc0d673",
        "link": "https://www.artwax.com.br/marcas/boina-de-microfibra-corte-com-interface-detailer-3-5-com-velcro",
        "marca": "Detailer",
        "fispq": null
    },
    {
        "nome": "Boina Polimento De Vidros Carpete 5\"",
        "descricao": "-",
        "preco": "R$ 54,90",
        "imagem": "https://images.tcdn.com.br/files/606785/themes/95/img/settings/casa.png?8d0a93ae6301f11fb3959efd9fc0d673",
        "link": "https://www.artwax.com.br/boina-polimento-de-vidros-carpete-5",
        "marca": "Vonixx",
        "fispq": null
    },
    {
        "nome": "Boina de Espuma Refino 5,5\" Sem Interface Detailer",
        "descricao": "Desenvolvida para uso com politriz rotativa e RotoOrbital na etapa Refino. Possui uma altura especial e desenho chanfrado facilitando a posição no suporte, sendo assim, reduz impactos e atritos nos contornos",
        "preco": "R$ 59,90",
        "imagem": "https://images.tcdn.com.br/files/606785/themes/95/img/settings/casa.png?8d0a93ae6301f11fb3959efd9fc0d673",
        "link": "https://www.artwax.com.br/marcas/detailer/boina-de-espuma-amarela-refino-5-5-detailer",
        "marca": "Detailer",
        "fispq": null
    },
    {
        "nome": "Boina de Espuma Refino 6,5\" Sem Interface Detailer",
        "descricao": "Desenvolvida para uso com politriz rotativa e Roto-orbital na etapa Refino. Possui uma altura especial e desenho chanfrado facilitando a posição no suporte, sendo assim, reduz impactos e atritos nos contornos",
        "preco": "R$ 62,90",
        "imagem": "https://images.tcdn.com.br/files/606785/themes/95/img/settings/casa.png?8d0a93ae6301f11fb3959efd9fc0d673",
        "link": "https://www.artwax.com.br/marcas/detailer/boina-de-espuma-amarela-refino-6-5-detailer",
        "marca": "Detailer",
        "fispq": null
    },
    {
        "nome": "Boina de Espuma Branca Refino 3\" Sem Interface Artwax",
        "descricao": "Descubra a Boina de Espuma Branca da Artwax, ideal para corte leve e refino em vernizes delicados, com espuma de alta qualidade da Alemanha para resultados profissionais",
        "preco": "R$ 28,90",
        "imagem": "https://images.tcdn.com.br/files/606785/themes/95/img/settings/casa.png?8d0a93ae6301f11fb3959efd9fc0d673",
        "link": "https://www.artwax.com.br/polimento/boinas/boina-refino/boina-de-espuma-branca-refino-3-artwax",
        "marca": "Artwax",
        "fispq": null
    },
    {
        "nome": "Boinas Microfibra Corte Com Interface 3,5\" e 6,5\" Detailer kit 2 Unidades",
        "descricao": "Kit de Boinas para uso profissional, aconselhamos o uso de interface para um corte mais suave e para polimento em peças desniveladas.",
        "preco": "R$ 89,80",
        "imagem": "https://images.tcdn.com.br/files/606785/themes/95/img/settings/casa.png?8d0a93ae6301f11fb3959efd9fc0d673",
        "link": "https://www.artwax.com.br/kits/kit-de-boinas-microfibra-corte-com-interface-3-5-e-6-5-detailer",
        "marca": "Detailer",
        "fispq": null
    },
    {
        "nome": "Clay Bar Mágico Disco de Descontaminação Suave 6\" Kers",
        "descricao": "Clay bar em disco, para uso manual ou na roto orbital",
        "preco": "R$ 169,90",
        "imagem": "https://images.tcdn.com.br/files/606785/themes/95/img/settings/casa.png?8d0a93ae6301f11fb3959efd9fc0d673",
        "link": "https://www.artwax.com.br/kers-clay-bar-magico-disco-de-descontaminacao-suave-6",
        "marca": "Kers",
        "fispq": null
    },
    {
        "nome": "Boina Face Unica com Eva Kawazaki 6\" For Detail",
        "descricao": "A Boina Face Única Com Interface de E.V.A 6? De Fio Especial For Detail são confeccionadas com fibras de alta qualidade e tecnologia exclusiva, que entregam um melhor corte e um acabamento com menores índices de holografia.",
        "preco": "R$ 69,00",
        "imagem": "https://images.tcdn.com.br/files/606785/themes/95/img/settings/casa.png?8d0a93ae6301f11fb3959efd9fc0d673",
        "link": "https://www.artwax.com.br/boina-face-unica-com-eva-kawazaki-6-for-detail",
        "marca": "FOR DETAIL",
        "fispq": null
    },
    {
        "nome": "Boina Dupla Face Kawazaki 6\" Fio Especial For Detail",
        "descricao": "-",
        "preco": "R$ 79,00",
        "imagem": "https://images.tcdn.com.br/files/606785/themes/95/img/settings/casa.png?8d0a93ae6301f11fb3959efd9fc0d673",
        "link": "https://www.artwax.com.br/boina-dupla-face-kawazaki-6-fio-especial-for-detail",
        "marca": "FOR DETAIL",
        "fispq": null
    },
    {
        "nome": "Boina Dupla Face Kawazaki 8\" Fio Especial For Detail",
        "descricao": "A Boina Dupla Face Kawasaki 8? De Fio Especial For Detail são confeccionadas com fibras de alta qualidade e tecnologia exclusiva, que entregam um melhor corte e um acabamento com menores índices de holografia.",
        "preco": "R$ 99,00",
        "imagem": "https://images.tcdn.com.br/files/606785/themes/95/img/settings/casa.png?8d0a93ae6301f11fb3959efd9fc0d673",
        "link": "https://www.artwax.com.br/boina-dupla-face-kawazaki-8-fio-especial-for-detail",
        "marca": "FOR DETAIL",
        "fispq": null
    },
    {
        "nome": "Boina Face Unica com Eva Kawazaki 5\" For Detail",
        "descricao": "-",
        "preco": "R$ 65,00",
        "imagem": "https://images.tcdn.com.br/files/606785/themes/95/img/settings/casa.png?8d0a93ae6301f11fb3959efd9fc0d673",
        "link": "https://www.artwax.com.br/boina-face-unica-com-eva-kawazaki-5-for-detail",
        "marca": "FOR DETAIL",
        "fispq": null
    },
    {
        "nome": "Boina Face Única sem Eva Kawazaki 6\" For Detail",
        "descricao": "-",
        "preco": "R$ 59,00",
        "imagem": "https://images.tcdn.com.br/files/606785/themes/95/img/settings/casa.png?8d0a93ae6301f11fb3959efd9fc0d673",
        "link": "https://www.artwax.com.br/boina-face-unica-sem-eva-kawazaki-6-for-detail",
        "marca": "FOR DETAIL",
        "fispq": null
    },
    {
        "nome": "Boina Face Única Sem E.V.A Kawazaki 5\" For Detail",
        "descricao": "-",
        "preco": "R$ 49,00",
        "imagem": "https://images.tcdn.com.br/files/606785/themes/95/img/settings/casa.png?8d0a93ae6301f11fb3959efd9fc0d673",
        "link": "https://www.artwax.com.br/boina-face-unica-sem-e-v-a-kawazaki-5-for-detail",
        "marca": "FOR DETAIL",
        "fispq": null
    },
    {
        "nome": "Kit de Boinas Voxer Corte Pesado Médio Refino e Lustro 6\" Vonixx 5 Unidades",
        "descricao": "-",
        "preco": "R$ 324,50",
        "imagem": "https://images.tcdn.com.br/files/606785/themes/95/img/settings/casa.png?8d0a93ae6301f11fb3959efd9fc0d673",
        "link": "https://www.artwax.com.br/polimento/kit-de-boinas-voxer-6-vonixx-5-unidades",
        "marca": "Vonixx",
        "fispq": null
    },
    {
        "nome": "Kit de Boinas Voxer Corte Pesado Médio Refino e Lustro 5\" Vonixx 5 Unidades",
        "descricao": "-",
        "preco": "R$ 299,50",
        "imagem": "https://images.tcdn.com.br/files/606785/themes/95/img/settings/casa.png?8d0a93ae6301f11fb3959efd9fc0d673",
        "link": "https://www.artwax.com.br/polimento/kit-de-boinas-voxer-5-vonixx-5-unidades",
        "marca": "Vonixx",
        "fispq": null
    },
    {
        "nome": "Kit Boinas Voxer 3\"",
        "descricao": "Kit com 5 boinas Voxer (Vonixx) de 3",
        "preco": "R$ 167,50",
        "imagem": "https://images.tcdn.com.br/files/606785/themes/95/img/settings/casa.png?8d0a93ae6301f11fb3959efd9fc0d673",
        "link": "https://www.artwax.com.br/polimento/kit-de-boinas-voxer-3-vonixx-4-unidades",
        "marca": "Vonixx",
        "fispq": null
    },
    {
        "nome": "Boina de Espuma Corte 6,5\" Sem Interface Detailer",
        "descricao": "Desenvolvida para uso com politriz rotativa e Roto-orbital na etapa corte. Possui uma altura especial e desenho chanfrado facilitando a posição no suporte, sendo assim, reduz impactos e atritos nos contornos da peça.",
        "preco": "R$ 62,90",
        "imagem": "https://images.tcdn.com.br/files/606785/themes/95/img/settings/casa.png?8d0a93ae6301f11fb3959efd9fc0d673",
        "link": "https://www.artwax.com.br/marcas/detailer/boina-de-espuma-laranja-corte-6-5-detailer",
        "marca": "Detailer",
        "fispq": null
    },
    {
        "nome": "Boina de Espuma Corte 5,5\" Sem Interface Detailer",
        "descricao": "Desenvolvida para uso com politriz rotativa e Roto-orbital na etapa corte. Possui uma altura especial e desenho chanfrado facilitando a posição no suporte, sendo assim, reduz impactos e atritos nos contornos da peça.",
        "preco": "R$ 59,90",
        "imagem": "https://images.tcdn.com.br/files/606785/themes/95/img/settings/casa.png?8d0a93ae6301f11fb3959efd9fc0d673",
        "link": "https://www.artwax.com.br/marcas/detailer/boina-de-espuma-laranja-corte-5-5-detailer",
        "marca": "Detailer",
        "fispq": null
    },
    {
        "nome": "Boina Para Polimento de Vidros 3\" Katana Detailer",
        "descricao": "Boina para Polimento de Vidros Detailer Katana remove de forma eficaz marcas da água, sujidades e arranhões do vidro exterior do veículo ao ser utilizada com um polidor de vidros.",
        "preco": "R$ 28,90",
        "imagem": "https://images.tcdn.com.br/files/606785/themes/95/img/settings/casa.png?8d0a93ae6301f11fb3959efd9fc0d673",
        "link": "https://www.artwax.com.br/boina-para-polimento-de-vidros-3-katana-detailer",
        "marca": "Detailer",
        "fispq": null
    },
    {
        "nome": "Boina de Espuma Laranja Corte 3\" Sem Interface Artwax",
        "descricao": "Explore a Boina de Espuma Laranja Corte 3",
        "preco": "R$ 28,90",
        "imagem": "https://images.tcdn.com.br/files/606785/themes/95/img/settings/casa.png?8d0a93ae6301f11fb3959efd9fc0d673",
        "link": "https://www.artwax.com.br/polimento/boinas/boina-corte/boina-de-espuma-laranja-corte-3-artwax",
        "marca": "Artwax",
        "fispq": null
    },
    {
        "nome": "Suporte Para Boina Flex Rotativa 1\" Rosca 5/8\" Vonixx",
        "descricao": "-",
        "preco": "R$ 44,90",
        "imagem": "https://images.tcdn.com.br/files/606785/themes/95/img/settings/casa.png?8d0a93ae6301f11fb3959efd9fc0d673",
        "link": "https://www.artwax.com.br/polimento/suporte-para-boina-flex-rotativa-1-rosca-58-vonixx",
        "marca": "Vonixx",
        "fispq": null
    },
    {
        "nome": "Suporte Ventilado Roto Orbital 6\" Voxer Rosca M8 Vonixx",
        "descricao": "Projetado para promover acabamento fino e resultados mais rápidos nas etapas de polimento na pintura automotiva.",
        "preco": "R$ 122,90",
        "imagem": "https://images.tcdn.com.br/files/606785/themes/95/img/settings/casa.png?8d0a93ae6301f11fb3959efd9fc0d673",
        "link": "https://www.artwax.com.br/vonixx-suporte-ventilado-roto-orbital-6-voxer-rosca-m8",
        "marca": "Vonixx",
        "fispq": null
    },
    {
        "nome": "Vonixx Suporte Ventilado Roto Orbital 5\" Voxer Rosca M8",
        "descricao": "Projetado para promover acabamento fino e resultados mais rápidos nas etapas de polimento na pintura automotiva.",
        "preco": "R$ 117,90",
        "imagem": "https://images.tcdn.com.br/files/606785/themes/95/img/settings/casa.png?8d0a93ae6301f11fb3959efd9fc0d673",
        "link": "https://www.artwax.com.br/vonixx-suporte-ventilado-roto-orbital-5-voxer-rosca-m8",
        "marca": "Vonixx",
        "fispq": null
    },
    {
        "nome": "Boina Para Polimento de Vidros 5\" Katana Detailer",
        "descricao": "Boina para Polimento de Vidros Detailer Katana remove de forma eficaz marcas da água, sujidades e arranhões do vidro exterior do veículo ao ser utilizada com um polidor de vidros.",
        "preco": "R$ 45,90",
        "imagem": "https://images.tcdn.com.br/files/606785/themes/95/img/settings/casa.png?8d0a93ae6301f11fb3959efd9fc0d673",
        "link": "https://www.artwax.com.br/boina-para-polimento-de-vidros-5-katana-detailer",
        "marca": "Detailer",
        "fispq": null
    },
    {
        "nome": "Boina De Espuma Branca Com Velcro Corte Agressivo 6\" For Detail",
        "descricao": "Poder de corte alinhado a um ótimo nivelamento da superfície. Nossa boina agressiva For Detail entrega alta tecnologia e durabilidade, pois é feita com espuma de poliuretano reticuladas importada da Alemanha",
        "preco": "R$ 74,90",
        "imagem": "https://images.tcdn.com.br/files/606785/themes/95/img/settings/casa.png?8d0a93ae6301f11fb3959efd9fc0d673",
        "link": "https://www.artwax.com.br/polimento/boinas/boina-corte/boina-de-espuma-agressiva-branca-corte-6-com-furo-for-detail",
        "marca": "FOR DETAIL",
        "fispq": null
    },
    {
        "nome": "Boina SDO CCS Azul Corte Sem Interface 5\" Lake Country",
        "descricao": "Patenteada em todo o mundo. Boinas SDO com tecnologia CCS. Projetada para oferecer as mesmas excelentes espumas de engenharia que a linha HDO CCS sem a construção de camada dupla.",
        "preco": "R$ 99,90",
        "imagem": "https://images.tcdn.com.br/files/606785/themes/95/img/settings/casa.png?8d0a93ae6301f11fb3959efd9fc0d673",
        "link": "https://www.artwax.com.br/boina-sdo-ccs-azul-corte-5-lake-country",
        "marca": "Lake Country",
        "fispq": null
    },
    {
        "nome": "Boina SDO CCS Preta Lustro Sem Interface 6\" Lake Country",
        "descricao": "Patenteada em todo o mundo. Boinas SDO com tecnologia CCS. Projetada para oferecer as mesmas excelentes espumas de engenharia que a linha HDO CCS sem a construção de camada dupla.",
        "preco": "R$ 114,90",
        "imagem": "https://images.tcdn.com.br/files/606785/themes/95/img/settings/casa.png?8d0a93ae6301f11fb3959efd9fc0d673",
        "link": "https://www.artwax.com.br/boina-sdo-ccs-preta-lustro-6-lake-country",
        "marca": "Lake Country",
        "fispq": null
    },
    {
        "nome": "Boina SDO CCS Preta Lustro Sem Interface 5\" Lake Country",
        "descricao": "Patenteada em todo o mundo. Boinas SDO com tecnologia CCS. Projetada para oferecer as mesmas excelentes espumas de engenharia que a linha HDO CCS sem a construção de camada dupla.",
        "preco": "R$ 99,90",
        "imagem": "https://images.tcdn.com.br/files/606785/themes/95/img/settings/casa.png?8d0a93ae6301f11fb3959efd9fc0d673",
        "link": "https://www.artwax.com.br/boina-sdo-ccs-preta-lustro-sem-interface-5-lake-country",
        "marca": "Lake Country",
        "fispq": null
    },
    {
        "nome": "Boina SDO CCS Laranja Refino Sem Interface 6\" Lake Country",
        "descricao": "Descrição não encontrada",
        "preco": "R$ 114,90",
        "imagem": "https://images.tcdn.com.br/files/606785/themes/95/img/settings/casa.png?8d0a93ae6301f11fb3959efd9fc0d673",
        "link": "https://www.artwax.com.br/boina-sdo-ccs-laranja-refino-6-lake-country",
        "marca": "Lake Country",
        "fispq": null
    },
    {
        "nome": "Boina SDO CCS Laranja Refino Sem Interface 5\" Lake Country",
        "descricao": "Patenteada em todo o mundo. Boinas SDO com tecnologia CCS. Projetada para oferecer as mesmas excelentes espumas de engenharia que a linha HDO CCS sem a construção de camada dupla.",
        "preco": "R$ 99,90",
        "imagem": "https://images.tcdn.com.br/files/606785/themes/95/img/settings/casa.png?8d0a93ae6301f11fb3959efd9fc0d673",
        "link": "https://www.artwax.com.br/boina-sdo-ccs-laranja-refino-5-lake-country",
        "marca": "Lake Country",
        "fispq": null
    },
    {
        "nome": "Boina de Algodão Suave 5\" Para Polimento De Vidros Mills",
        "descricao": "-",
        "preco": "R$ 50,00",
        "imagem": "https://images.tcdn.com.br/files/606785/themes/95/img/settings/casa.png?8d0a93ae6301f11fb3959efd9fc0d673",
        "link": "https://www.artwax.com.br/polimento/polidores/boina-de-algodao-suave-5",
        "marca": "Mills",
        "fispq": null
    },
    {
        "nome": "Boina de Algodão Suave 3\" Para Polimento De Vidros Mills",
        "descricao": "-",
        "preco": "R$ 33,00",
        "imagem": "https://images.tcdn.com.br/files/606785/themes/95/img/settings/casa.png?8d0a93ae6301f11fb3959efd9fc0d673",
        "link": "https://www.artwax.com.br/polimento/boina-de-algodao-suave-3",
        "marca": "Mills",
        "fispq": null
    },
    {
        "nome": "Boinas SDO CCS 5\" Corte Refino Lustro Lake Country Kit 3 Unidades",
        "descricao": "Patenteada em todo o mundo. Boinas SDO com tecnologia CCS. Projetada para oferecer as mesmas excelentes espumas de engenharia que a linha HDO CCS sem a construção de camada dupla.",
        "preco": "R$ 299,70",
        "imagem": "https://images.tcdn.com.br/files/606785/themes/95/img/settings/casa.png?8d0a93ae6301f11fb3959efd9fc0d673",
        "link": "https://www.artwax.com.br/polimento/kit-boinas-sdo-ccs-5-corte-refino-lustro-lc-3-unidades",
        "marca": "Lake Country",
        "fispq": null
    },
    {
        "nome": "Boina de Espuma Force Macia 3,5\" Lustro Cadillac",
        "descricao": "",
        "preco": "R$ 69,90",
        "imagem": "https://images.tcdn.com.br/files/606785/themes/95/img/settings/casa.png?8d0a93ae6301f11fb3959efd9fc0d673",
        "link": "https://www.artwax.com.br/cadillac-boina-de-espuma-force-macia-3-5-corte",
        "marca": "Cadillac",
        "fispq": null
    },
    {
        "nome": "Boina de Espuma Force Media Branca 3,5\" Refino Sem Interface Cadillac",
        "descricao": "",
        "preco": "R$ 39,90",
        "imagem": "https://images.tcdn.com.br/files/606785/themes/95/img/settings/casa.png?8d0a93ae6301f11fb3959efd9fc0d673",
        "link": "https://www.artwax.com.br/cadillac-boina-de-espuma-force-media-branca-3-5-corte",
        "marca": "Cadillac",
        "fispq": null
    },
    {
        "nome": "Politriz Roto Orbital 5\" SGT-Colors 15MM Rosa SGT-5118 220V Sigma Tools",
        "descricao": "A Politriz Roto Orbital Colors SGT-5118 Da Sigma Tools é a ferramenta ideal para restaurar o brilho original do seu carro e um perfeito acabamento. Sua tecnologia roto orbital produz movimentos circulares e orbitais garantindo um polimento uniforme.",
        "preco": "R$ 699,00",
        "imagem": "https://images.tcdn.com.br/files/606785/themes/95/img/settings/casa.png?8d0a93ae6301f11fb3959efd9fc0d673",
        "link": "https://www.artwax.com.br/marcas/politriz-roto-orbital-5-sgt-colors-15mm-rosa-sgt-5118-220v-sigma-tools",
        "marca": "SIGMA TOOLS",
        "fispq": null
    },
    {
        "nome": "Politriz Roto Orbital 5\" Colors 15MM Rosa SGT-5118 110V Sigma Tools",
        "descricao": "A Politriz Roto Orbital Colors SGT-5118 Da Sigma Tools é a ferramenta ideal para restaurar o brilho original do seu carro e um perfeito acabamento. Sua tecnologia roto orbital produz movimentos circulares e orbitais garantindo um polimento uniforme.",
        "preco": "R$ 699,00",
        "imagem": "https://images.tcdn.com.br/files/606785/themes/95/img/settings/casa.png?8d0a93ae6301f11fb3959efd9fc0d673",
        "link": "https://www.artwax.com.br/marcas/politriz-roto-orbital-5-colors-15mm-rosa-sgt-5118-110v-sigma-tools",
        "marca": "SIGMA TOOLS",
        "fispq": null
    },
    {
        "nome": "Politriz Roto Orbital 5\" SGT-Colors 15MM Amarela SGT-5118 220V Sigma Tools",
        "descricao": "A Politriz Roto Orbital Colors SGT-5118 Da Sigma Tools é a ferramenta ideal para restaurar o brilho original do seu carro e um perfeito acabamento. Sua tecnologia roto orbital produz movimentos circulares e orbitais garantindo um polimento uniforme.",
        "preco": "R$ 699,00",
        "imagem": "https://images.tcdn.com.br/files/606785/themes/95/img/settings/casa.png?8d0a93ae6301f11fb3959efd9fc0d673",
        "link": "https://www.artwax.com.br/marcas/politriz-roto-orbital-5-colors-15mm-amarela-sgt-5118-220v-sigma-tools",
        "marca": "SIGMA TOOLS",
        "fispq": null
    },
    {
        "nome": "Politriz Roto Orbital 5\" Colors 15MM Amarela SGT-5118 110V Sigma Tools",
        "descricao": "A Politriz Roto Orbital Colors SGT-5118 Da Sigma Tools é a ferramenta ideal para restaurar o brilho original do seu carro e um perfeito acabamento. Sua tecnologia roto orbital produz movimentos circulares e orbitais garantindo um polimento uniforme.",
        "preco": "R$ 699,00",
        "imagem": "https://images.tcdn.com.br/files/606785/themes/95/img/settings/casa.png?8d0a93ae6301f11fb3959efd9fc0d673",
        "link": "https://www.artwax.com.br/marcas/politriz-roto-orbital-5-colors-15mm-amarela-sgt-5118-110v-sigma-tools",
        "marca": "SIGMA TOOLS",
        "fispq": null
    },
    {
        "nome": "Politriz Roto Orbital 5\" Colors 15MM Azul SGT-5118 220V Sigma Tools",
        "descricao": "A Politriz Roto Orbital Colors SGT-5118 Da Sigma Tools é a ferramenta ideal para restaurar o brilho original do seu carro e um perfeito acabamento. Sua tecnologia roto orbital produz movimentos circulares e orbitais garantindo um polimento uniforme.",
        "preco": "R$ 699,00",
        "imagem": "https://images.tcdn.com.br/files/606785/themes/95/img/settings/casa.png?8d0a93ae6301f11fb3959efd9fc0d673",
        "link": "https://www.artwax.com.br/marcas/politriz-roto-orbital-5-colors-15mm-azul-sgt-5118-220v-sigma-tools",
        "marca": "SIGMA TOOLS",
        "fispq": null
    },
    {
        "nome": "Politriz Roto Orbital 5\" Colors 15MM Laranja SGT-5118 110V Sigma Tools",
        "descricao": "A Politriz Roto Orbital Colors SGT-5118 Da Sigma Tools é a ferramenta ideal para restaurar o brilho original do seu carro e um perfeito acabamento. Sua tecnologia roto orbital produz movimentos circulares e orbitais garantindo um polimento uniforme.",
        "preco": "R$ 699,00",
        "imagem": "https://images.tcdn.com.br/files/606785/themes/95/img/settings/casa.png?8d0a93ae6301f11fb3959efd9fc0d673",
        "link": "https://www.artwax.com.br/marcas/politriz-roto-orbital-5-colors-15mm-110v-laranja-sgt-5118-sigma-tools",
        "marca": "SIGMA TOOLS",
        "fispq": null
    },
    {
        "nome": "Politriz Roto Orbital 5\" Colors 15MM Preta SGT-5118 220V Sigma Tools",
        "descricao": "A Politriz Roto Orbital Colors SGT-5118 Da Sigma Tools é a ferramenta ideal para restaurar o brilho original do seu carro e um perfeito acabamento. Sua tecnologia roto orbital produz movimentos circulares e orbitais garantindo um polimento uniforme.",
        "preco": "R$ 909,90",
        "imagem": "https://images.tcdn.com.br/files/606785/themes/95/img/settings/casa.png?8d0a93ae6301f11fb3959efd9fc0d673",
        "link": "https://www.artwax.com.br/marcas/politriz-roto-orbital-5-colors-15mm-preta-sgt-5118-220v-sigma-tools",
        "marca": "SIGMA TOOLS",
        "fispq": null
    },
    {
        "nome": "Politriz Roto Orbital 5\" Colors 15MM Preta SGT-5118 110V Sigma Tools",
        "descricao": "A Politriz Roto Orbital Colors SGT-5118 Da Sigma Tools é a ferramenta ideal para restaurar o brilho original do seu carro e um perfeito acabamento. Sua tecnologia roto orbital produz movimentos circulares e orbitais garantindo um polimento uniforme.",
        "preco": "R$ 909,90",
        "imagem": "https://images.tcdn.com.br/files/606785/themes/95/img/settings/casa.png?8d0a93ae6301f11fb3959efd9fc0d673",
        "link": "https://www.artwax.com.br/marcas/politriz-roto-orbital-15mm-colors-sgt-preta-110v",
        "marca": "SIGMA TOOLS",
        "fispq": null
    },
    {
        "nome": "Boina de Espuma Polishing Pad Laranja 3\" Lustro Carpro",
        "descricao": "A CARPRO Orange Polishing Pad é feita de uma espuma de célula aberta projetada especificamente para polimento médio em muitos tipos de tinta, a camada intermediária de espuma elastomérica densa oferece a capacidade de manter facilmente uma pressão uniform",
        "preco": "R$ 83,64",
        "imagem": "https://images.tcdn.com.br/files/606785/themes/95/img/settings/casa.png?8d0a93ae6301f11fb3959efd9fc0d673",
        "link": "https://www.artwax.com.br/polimento/boinas/boina-lustro/boina-de-espuma-polishing-pad-orange-3-lustro-carpro",
        "marca": "Carpro",
        "fispq": null
    },
    {
        "nome": "Politriz Rotativa 5\" SGT-5127 Red & Shine 1.200W Sigma Tools 110V",
        "descricao": "Politriz Rotativa 5",
        "preco": "R$ 899,00",
        "imagem": "https://images.tcdn.com.br/files/606785/themes/95/img/settings/casa.png?8d0a93ae6301f11fb3959efd9fc0d673",
        "link": "https://www.artwax.com.br/maquinas-e-equipamentos/politriz-rotativa-5-red-amp-shine-1-200-watts-sgt-5127-110v-sigma-tools",
        "marca": "SIGMA TOOLS",
        "fispq": null
    },
    {
        "nome": "Boina Alumina Lustro 165mm 6\" Easytech",
        "descricao": "As boinas de espuma Alumina são produzidas pela Scholl Concepts, em uma das maiores fábricas de boinas do mundo, em REMSEK.",
        "preco": "R$ 80,65",
        "imagem": "https://images.tcdn.com.br/files/606785/themes/95/img/settings/casa.png?8d0a93ae6301f11fb3959efd9fc0d673",
        "link": "https://www.artwax.com.br/marcas/easytech/easytech-boina-alumina-lustro-165mm-6",
        "marca": "Easytech",
        "fispq": null
    },
    {
        "nome": "Boina de Lã Corte Pesado Pirulito Com Interface 6\" Lincoln",
        "descricao": "Boina de Lã Corte Pesado SV Pirulito Power com Interface Para Rotativa 6",
        "preco": "R$ 84,90",
        "imagem": "https://images.tcdn.com.br/files/606785/themes/95/img/settings/casa.png?8d0a93ae6301f11fb3959efd9fc0d673",
        "link": "https://www.artwax.com.br/polimento/boinas/boina-corte/boina-de-la-corte-pesado-sv-pirulito-power-com-interface-para-rotativa-6-lincoln",
        "marca": "Lincoln",
        "fispq": null
    },
    {
        "nome": "Boina de Espuma Flat Azul  Refino Lustro Sem Interface 6\" Lincoln",
        "descricao": "Seu conceito é moderno, eficiente e econômico sem perder a máxima qualidade, que é a característica dos produtos Lincoln Polidores.",
        "preco": "Preço não encontrado",
        "imagem": "https://images.tcdn.com.br/files/606785/themes/95/img/settings/casa.png?8d0a93ae6301f11fb3959efd9fc0d673",
        "link": "https://www.artwax.com.br/polimento/boinas/boina-refino/boina-de-espuma-flat-azul-6-refino-lincoln",
        "marca": "Lincoln",
        "fispq": null
    },
    {
        "nome": "Boina de Espuma Flat Laranja Corte Leve Refino Sem Interface 6\" Lincoln",
        "descricao": "Seu conceito é moderno, eficiente e econômico sem perder a máxima qualidade, que é a característica dos produtos Lincoln Polidores.",
        "preco": "Preço não encontrado",
        "imagem": "https://images.tcdn.com.br/files/606785/themes/95/img/settings/casa.png?8d0a93ae6301f11fb3959efd9fc0d673",
        "link": "https://www.artwax.com.br/polimento/boinas/boina-corte/boina-de-espuma-flat-laranja-6-corte-lincoln",
        "marca": "Lincoln",
        "fispq": null
    },
    {
        "nome": "Boina de Espuma Corte Leve 6,5\" Sem Interface Detailer",
        "descricao": "A proposta dessa boina é tornar eficiente a etapa de corte leve/refinado evitando uso excessivo de produtos",
        "preco": "Preço não encontrado",
        "imagem": "https://images.tcdn.com.br/files/606785/themes/95/img/settings/casa.png?8d0a93ae6301f11fb3959efd9fc0d673",
        "link": "https://www.artwax.com.br/marcas/detailer/boina-de-espuma-azul-corte-leve-6-5-detailer",
        "marca": "Detailer",
        "fispq": null
    },
    {
        "nome": "Boina de Espuma Corte Leve 5,5\" Sem Interface Detailer",
        "descricao": "A proposta dessa boina é tornar eficiente a etapa de corte leve/refinado evitando uso excessivo de produtos",
        "preco": "Preço não encontrado",
        "imagem": "https://images.tcdn.com.br/files/606785/themes/95/img/settings/casa.png?8d0a93ae6301f11fb3959efd9fc0d673",
        "link": "https://www.artwax.com.br/marcas/detailer/boina-de-espuma-azul-corte-leve-5-5-detailer",
        "marca": "Detailer",
        "fispq": null
    },
    {
        "nome": "Boina Dupla Face Fio Macia 8\" Amarela  320171 Lincoln",
        "descricao": "A Lincoln emprega tecnologia diferenciada e controlada, fabricando o disco plástico e o inserto metálico. Na junção das faces da boina são utilizados adesivos do mais alto padrão que proporcionam alta resistência e flexibilidade ao produto.",
        "preco": "Preço não encontrado",
        "imagem": "https://images.tcdn.com.br/files/606785/themes/95/img/settings/casa.png?8d0a93ae6301f11fb3959efd9fc0d673",
        "link": "https://www.artwax.com.br/boina-de-espuma-8-dupla-face-fio-macia-amarelo-320171-lincoln",
        "marca": "Lincoln",
        "fispq": null
    },
    {
        "nome": "Boina de Lã Híbrida Corte 5\" Sem Interface For Detail",
        "descricao": "A Boina De Lã Híbrida 5? Para Corte For Detail é o acessório ideal para detalhadores que buscam um corte agressivo e eficiente em seus projetos de polimento. Compatível com diversos produtos e diferentes compostos de polimento.",
        "preco": "Preço não encontrado",
        "imagem": "https://images.tcdn.com.br/files/606785/themes/95/img/settings/casa.png?8d0a93ae6301f11fb3959efd9fc0d673",
        "link": "https://www.artwax.com.br/polimento/boinas/boina-corte/boina-de-la-hibrida-mista-branca-para-roto-orbital-5-130mm-for-detail",
        "marca": "FOR DETAIL",
        "fispq": null
    },
    {
        "nome": "Boina de Carpete Para Polimento de Vidro 3\" Resolvidro",
        "descricao": "Boina de Carpete Para Polimento de Vidro 3",
        "preco": "Preço não encontrado",
        "imagem": "https://images.tcdn.com.br/files/606785/themes/95/img/settings/casa.png?8d0a93ae6301f11fb3959efd9fc0d673",
        "link": "https://www.artwax.com.br/boina-de-carpete-para-polimento-de-vidro-3-resolvidro",
        "marca": "RESOLVIDRO",
        "fispq": null
    },
    {
        "nome": "Measure Frasco de Dosagem 100ML Carpro",
        "descricao": "-",
        "preco": "Preço não encontrado",
        "imagem": "https://images.tcdn.com.br/files/606785/themes/95/img/settings/casa.png?8d0a93ae6301f11fb3959efd9fc0d673",
        "link": "https://www.artwax.com.br/measure-frasco-de-dosagem-100ml-carpro",
        "marca": "Carpro",
        "fispq": null
    },
    {
        "nome": "Boina Jeans Hard Cut Corte Pesado 5\" Com Interface Detailer",
        "descricao": "Indicada para uso com máquina Roto-Orbital para remover",
        "preco": "Preço não encontrado",
        "imagem": "https://images.tcdn.com.br/files/606785/themes/95/img/settings/casa.png?8d0a93ae6301f11fb3959efd9fc0d673",
        "link": "https://www.artwax.com.br/polimento/boinas/boina-corte/boina-jeans-hard-cut-corte-pesado-5-detailer",
        "marca": "Detailer",
        "fispq": null
    },
    {
        "nome": "Boinas Jeans Hard Cut Corte Pesado 3\" e 5\" Detailer Kit 2 Unidades",
        "descricao": "Indicada para uso com máquina Roto-Orbital para remover",
        "preco": "Preço não encontrado",
        "imagem": "https://images.tcdn.com.br/files/606785/themes/95/img/settings/casa.png?8d0a93ae6301f11fb3959efd9fc0d673",
        "link": "https://www.artwax.com.br/kits/kit-boinas-jeans-hard-cut-corte-pesado-detailer-3-e-5",
        "marca": "Detailer",
        "fispq": null
    },
    {
        "nome": "Boina De Espuma Branca Com Velcro Lustro 6\" Polimento For Detail",
        "descricao": "A Boina De Espuma Branca 6? Para Lustro da For Detail é a escolha perfeita para que busca um acabamento profissional e impecável na pintura do veículo. Sua espuma macia possui densidade ideal, garantindo um polimento suave e eficaz.",
        "preco": "Preço não encontrado",
        "imagem": "https://images.tcdn.com.br/files/606785/themes/95/img/settings/casa.png?8d0a93ae6301f11fb3959efd9fc0d673",
        "link": "https://www.artwax.com.br/polimento/boinas/boina-lustro/boina-espuma-de-lustro-6-com-furo-for-detail",
        "marca": "FOR DETAIL",
        "fispq": null
    },
    {
        "nome": "Boina Espuma de Lustro 5\" Sem Interface For Detail",
        "descricao": "A Boina De Espuma Branca 5? Para Lustro da For Detail é a escolha perfeita para que busca um acabamento profissional e impecável na pintura do veículo. Sua espuma macia possui densidade ideal, garantindo um polimento suave e eficaz.",
        "preco": "Preço não encontrado",
        "imagem": "https://images.tcdn.com.br/files/606785/themes/95/img/settings/casa.png?8d0a93ae6301f11fb3959efd9fc0d673",
        "link": "https://www.artwax.com.br/polimento/boinas/boina-lustro/boina-espuma-de-lustro-preta-5-127mm-com-furo-for-detail",
        "marca": "FOR DETAIL",
        "fispq": null
    },
    {
        "nome": "Boina de Lã Hibrida Corte 5\" Sem Interface Artwax",
        "descricao": "Descubra a Boina de Lã Híbrida Corte 5",
        "preco": "Preço não encontrado",
        "imagem": "https://images.tcdn.com.br/files/606785/themes/95/img/settings/casa.png?8d0a93ae6301f11fb3959efd9fc0d673",
        "link": "https://www.artwax.com.br/polimento/boinas/boina-corte/boina-de-la-hibrida-corte-5-sem-interface-artwax",
        "marca": "Vonixx",
        "fispq": null
    },
    {
        "nome": "Boina de Lã Curta Média Hyper 5\" Com Interface Kers",
        "descricao": "-",
        "preco": "Preço não encontrado",
        "imagem": "https://images.tcdn.com.br/files/606785/themes/95/img/settings/casa.png?8d0a93ae6301f11fb3959efd9fc0d673",
        "link": "https://www.artwax.com.br/polimento/boinas/boina-corte/kers-boina-de-la-curta-hyper-5-media",
        "marca": "Kers",
        "fispq": null
    },
    {
        "nome": "Jogo de Boinas 5\" Espuma e Lã Hyper Kit 4 Unidades Kers",
        "descricao": "As boinas de espuma para polimento Hyper possui cortes hexagonais por sua base, esses cortes permitem a melhor performance na hora do polimento",
        "preco": "Preço não encontrado",
        "imagem": "https://images.tcdn.com.br/files/606785/themes/95/img/settings/casa.png?8d0a93ae6301f11fb3959efd9fc0d673",
        "link": "https://www.artwax.com.br/kers-boina-de-la-curta-hyper-5-agressiva-corte-pesado",
        "marca": "Kers",
        "fispq": null
    },
    {
        "nome": "Politriz Roto Orbital 15mm 5\" 900W -220V Com Suporte de Parede + Composto Polidor One 3 em 1 500ml For Detail Kit 3 itens",
        "descricao": "Robusta, leve, versátil e mais precisa. Possui 6 velocidades, chegando até 4800rpm, conta com  motor de 900w de potência. Possuí empunhadura ergonômica de fácil remoção, gatilho travável e cabo de energia em silicone de 5m flexível.",
        "preco": "Preço não encontrado",
        "imagem": "https://images.tcdn.com.br/files/606785/themes/95/img/settings/casa.png?8d0a93ae6301f11fb3959efd9fc0d673",
        "link": "https://www.artwax.com.br/kits/kit-politriz-roto-orbital-15mm-5-900w-220v-com-suporte-de-parede-composto-polidor-one-3-em-1-500ml-for-detail",
        "marca": "FOR DETAIL",
        "fispq": null
    },
    {
        "nome": "Politriz Roto Orbital 15mm 5\" 900W -110V Com Suporte de Parede + Composto Polidor One 3 em 1 500ml For Detail Kit 3 itens",
        "descricao": "Robusta, leve, versátil e mais precisa. Possui 6 velocidades, chegando até 4800rpm, conta com  motor de 900w de potência. Possuí empunhadura ergonômica de fácil remoção, gatilho travável e cabo de energia em silicone de 5m flexível.",
        "preco": "Preço não encontrado",
        "imagem": "https://images.tcdn.com.br/files/606785/themes/95/img/settings/casa.png?8d0a93ae6301f11fb3959efd9fc0d673",
        "link": "https://www.artwax.com.br/kits/kit-politriz-roto-orbital-15mm-5-900w-110v-com-suporte-de-parede-composto-polidor-one-3-em-1-500ml-for-detail",
        "marca": "FOR DETAIL",
        "fispq": null
    },
    {
        "nome": "Kit Politriz Orbital 5\" Voxer 15mm 220v + Compostos Polidores - Revelax e Limpa Boinas Vonixx",
        "descricao": "Kit Politriz Orbital 5",
        "preco": "Preço não encontrado",
        "imagem": "https://images.tcdn.com.br/files/606785/themes/95/img/settings/casa.png?8d0a93ae6301f11fb3959efd9fc0d673",
        "link": "https://www.artwax.com.br/kits/kit-politriz-orbital-5-voxer-15mm-220v-compostos-polidores-revelax-e-limpa-boinas-vonixx",
        "marca": "Vonixx",
        "fispq": null
    },
    {
        "nome": "Politriz Roto Orbital 15mm 5\" 900W/60Hz 110v + Jogo de Boinas Artwax e Composto Polidor For Detail Kit 6 Unidades",
        "descricao": "Kit Politriz Roto Orbital 15mm 5",
        "preco": "Preço não encontrado",
        "imagem": "https://images.tcdn.com.br/files/606785/themes/95/img/settings/casa.png?8d0a93ae6301f11fb3959efd9fc0d673",
        "link": "https://www.artwax.com.br/kits/kit-politriz-roto-orbital-15mm-5-900w60hz-110v-jogo-de-boinas-e-composto-polidor-fordtail",
        "marca": "FOR DETAIL",
        "fispq": null
    },
    {
        "nome": "Politriz Roto Orbital 15mm 5\" 900W/60Hz 220v + Jogo de Boinas Artwax e Composto Polidor For Detail Kit 6 Unidades",
        "descricao": "Kit Politriz Roto Orbital 15mm 5",
        "preco": "Preço não encontrado",
        "imagem": "https://images.tcdn.com.br/files/606785/themes/95/img/settings/casa.png?8d0a93ae6301f11fb3959efd9fc0d673",
        "link": "https://www.artwax.com.br/kits/kit-politriz-roto-orbital-15mm-5-900w60hz-220v-jogo-de-boinas-e-composto-polidor-fordtail",
        "marca": "FOR DETAIL",
        "fispq": null
    },
    {
        "nome": "Boina de Microfibra Corte Com Interface Detailer 5,5\" Com Velcro",
        "descricao": "Boina Microfibra Com Interface",
        "preco": "Preço não encontrado",
        "imagem": "https://images.tcdn.com.br/files/606785/themes/95/img/settings/casa.png?8d0a93ae6301f11fb3959efd9fc0d673",
        "link": "https://www.artwax.com.br/marcas/boina-de-microfibra-corte-com-interface-detailer-5-5-com-velcro",
        "marca": "Detailer",
        "fispq": null
    },
    {
        "nome": "Politriz Roto Orbital Gold Yes Tools 15mm 110v Kers + Jogo de Boinas Artwax 5\" Kit 5 Unidades",
        "descricao": "Kers Politriz Roto Orbital Gold Yes Tools 15mm 110v + Jogo de Boinas For Detail 5",
        "preco": "Preço não encontrado",
        "imagem": "https://images.tcdn.com.br/files/606785/themes/95/img/settings/casa.png?8d0a93ae6301f11fb3959efd9fc0d673",
        "link": "https://www.artwax.com.br/kits/kers-politriz-roto-orbital-gold-yes-tools-15mm-110v-jogo-de-boinas-for-detail-5",
        "marca": "Kers",
        "fispq": null
    },
    {
        "nome": "Boina de Espuma Branca Refino 5\" Sem Interface Artwax",
        "descricao": "Descubra a Boina de Espuma Branca da Artwax, ideal para corte leve e refino em vernizes delicados, com espuma de alta qualidade da Alemanha para resultados profissionais.",
        "preco": "Preço não encontrado",
        "imagem": "https://images.tcdn.com.br/files/606785/themes/95/img/settings/casa.png?8d0a93ae6301f11fb3959efd9fc0d673",
        "link": "https://www.artwax.com.br/polimento/boinas/boina-refino/boina-de-espuma-branca-refino-5-artwax",
        "marca": "Artwax",
        "fispq": null
    },
    {
        "nome": "Kit de Boinas Microfibra Corte com Interface 3,5\" e 5,5\" Detailer",
        "descricao": "-",
        "preco": "Preço não encontrado",
        "imagem": "https://images.tcdn.com.br/files/606785/themes/95/img/settings/casa.png?8d0a93ae6301f11fb3959efd9fc0d673",
        "link": "https://www.artwax.com.br/kits/kit-de-boinas-microfibra-corte-com-interface-3-5-e-5-5-detailer",
        "marca": "Detailer",
        "fispq": null
    },
    {
        "nome": "Boina de Espuma Lustro 5,5\" Sem Interface Detailer",
        "descricao": "Desenvolvida para uso com politriz rotativa e Roto-orbital na etapa lustro. Possui uma altura especial e desenho chanfrado facilitando a posição no suporte, sendo assim, reduz impactos e atritos nos contornos da peça.",
        "preco": "Preço não encontrado",
        "imagem": "https://images.tcdn.com.br/files/606785/themes/95/img/settings/casa.png?8d0a93ae6301f11fb3959efd9fc0d673",
        "link": "https://www.artwax.com.br/marcas/detailer/boina-de-espuma-verde-lustro-5-5-detailer",
        "marca": "Detailer",
        "fispq": null
    },
    {
        "nome": "Boina de Espuma Lustro 6,5\" Sem Interface Detailer",
        "descricao": "Desenvolvida para uso com politriz rotativa e Roto-orbital na etapa lustro. Possui uma altura especial e desenho chanfrado facilitando a posição no suporte, sendo assim, reduz impactos e atritos nos contornos da peça.",
        "preco": "Preço não encontrado",
        "imagem": "https://images.tcdn.com.br/files/606785/themes/95/img/settings/casa.png?8d0a93ae6301f11fb3959efd9fc0d673",
        "link": "https://www.artwax.com.br/marcas/detailer/boina-de-espuma-verde-lustro-6-5-detailer",
        "marca": "Detailer",
        "fispq": null
    },
    {
        "nome": "Kit Politriz Roto Orbital 15mm Giro Livre Red & Shine SGT 5116 220V 900w Sigma Tools + Jogo de Boinas 5\" Artwax",
        "descricao": "Kit Politriz Roto Orbital 15mm Red & Shine SGT 5116 - 220v 900w Sigma Tools + Jogo de Boinas For Detail 5",
        "preco": "Preço não encontrado",
        "imagem": "https://images.tcdn.com.br/files/606785/themes/95/img/settings/casa.png?8d0a93ae6301f11fb3959efd9fc0d673",
        "link": "https://www.artwax.com.br/kits/politriz-roto-orbital-15mm-red-shine-sgt-5116-220v-900w-sigma-tools-jogo-de-boinas-for-detail-5",
        "marca": "SIGMA TOOLS",
        "fispq": null
    },
    {
        "nome": "Politriz Roto Orbital 15mm Giro Livre Red & Shine SGT 5116 - 110v 900w Sigma Tools + Jogo de Boinas Artwax 5\" Kit  5 Unidades",
        "descricao": "Kit Politriz Roto Orbital 15mm Red & Shine SGT 5116 - 110v 900w Sigma Tools + Jogo de Boinas For Detail 5",
        "preco": "Preço não encontrado",
        "imagem": "https://images.tcdn.com.br/files/606785/themes/95/img/settings/casa.png?8d0a93ae6301f11fb3959efd9fc0d673",
        "link": "https://www.artwax.com.br/kits/politriz-roto-orbital-15mm-red-shine-sgt-5116-110v-900w-sigma-tools-jogo-de-boinas-for-detail-5",
        "marca": "SIGMA TOOLS",
        "fispq": null
    },
    {
        "nome": "Politriz Roto Orbital 15mm 5\" 900W/60Hz For Detail - 220V",
        "descricao": "A Politriz Roto Orbital da For Detail é a ferramenta ideal para um acabamento profissional e impecável. Com design robusto e durável, construída com materiais de alta qualidade para prolongar a vida útil.",
        "preco": "Preço não encontrado",
        "imagem": "https://images.tcdn.com.br/files/606785/themes/95/img/settings/casa.png?8d0a93ae6301f11fb3959efd9fc0d673",
        "link": "https://www.artwax.com.br/maquinas-e-equipamentos/politriz-e-roto-orbital/politriz-roto-orbital-15mm-5-sgt5116-220v-900w60hz-for-detail",
        "marca": "FOR DETAIL",
        "fispq": null
    },
    {
        "nome": "Boina de Espuma Super Lustro 6,5\" Sem Interface Detailer",
        "descricao": "Foi desenvolvida para uso com politriz rotativa ou Roto-orbital na etapa de lustro e super lustro ou enceramento premium com ceras Liquidas.",
        "preco": "Preço não encontrado",
        "imagem": "https://images.tcdn.com.br/files/606785/themes/95/img/settings/casa.png?8d0a93ae6301f11fb3959efd9fc0d673",
        "link": "https://www.artwax.com.br/marcas/detailer/boina-de-espuma-vermelha-super-macia-6-5-detailer",
        "marca": "Detailer",
        "fispq": null
    },
    {
        "nome": "Boina de Espuma Polishing Pad Laranja 5\" Refino - Lustro Carpro",
        "descricao": "Descubra a CARPRO Orange Polishing Pad e obtenha um polimento impecável do seu carro com uma boina de espuma de alta densidade, perfil chanfrado e",
        "preco": "Preço não encontrado",
        "imagem": "https://images.tcdn.com.br/files/606785/themes/95/img/settings/casa.png?8d0a93ae6301f11fb3959efd9fc0d673",
        "link": "https://www.artwax.com.br/boina-de-espuma-laranja-corte-5-5-detailer",
        "marca": "Carpro",
        "fispq": null
    },
    {
        "nome": "Boina Speed Polish Lã Natural Nobre Car 1\" Corte  - 2un",
        "descricao": "Seu sistema de impacto facilita o processo de polimento e minimiza o aquecimento, pode ser utilizada em politriz rotativa e/ ou roto orbital",
        "preco": "Preço não encontrado",
        "imagem": "https://images.tcdn.com.br/files/606785/themes/95/img/settings/casa.png?8d0a93ae6301f11fb3959efd9fc0d673",
        "link": "https://www.artwax.com.br/boina-speed-polish-la-natural-nobre-car-1-corte",
        "marca": "Nobre Car",
        "fispq": null
    },
    {
        "nome": "Lixadeira Orbital 6\" com Aspiração SGT-0319",
        "descricao": "A Lixadeira Orbital 6",
        "preco": "Preço não encontrado",
        "imagem": "https://images.tcdn.com.br/files/606785/themes/95/img/settings/casa.png?8d0a93ae6301f11fb3959efd9fc0d673",
        "link": "https://www.artwax.com.br/marcas/sgt-0319-lixadeira-orbital-6-com-aspiracao",
        "marca": "SIGMA TOOLS",
        "fispq": null
    },
    {
        "nome": "Boina de Espuma Preta Lustro 5\" Sem Interface Artwax",
        "descricao": "Conheça a Boina de Espuma Preta Lustro 5",
        "preco": "Preço não encontrado",
        "imagem": "https://images.tcdn.com.br/files/606785/themes/95/img/settings/casa.png?8d0a93ae6301f11fb3959efd9fc0d673",
        "link": "https://www.artwax.com.br/polimento/boinas/boina-lustro/boina-de-espuma-preta-lustro-5-artwax",
        "marca": "Artwax",
        "fispq": null
    },
    {
        "nome": "Boina de Espuma Laranja Corte 5\" Sem Interface Artwax",
        "descricao": "Explore a Boina de Espuma Laranja Corte 5",
        "preco": "Preço não encontrado",
        "imagem": "https://images.tcdn.com.br/files/606785/themes/95/img/settings/casa.png?8d0a93ae6301f11fb3959efd9fc0d673",
        "link": "https://www.artwax.com.br/polimento/boinas/boina-corte/boina-de-espuma-laranja-corte-5-artwax",
        "marca": "Artwax",
        "fispq": null
    },
    {
        "nome": "Boina de Espuma Preta Lustro 3 \" Sem Interface Artwax",
        "descricao": "Conheça a Boina de Espuma Preta Lustro 3",
        "preco": "Preço não encontrado",
        "imagem": "https://images.tcdn.com.br/files/606785/themes/95/img/settings/casa.png?8d0a93ae6301f11fb3959efd9fc0d673",
        "link": "https://www.artwax.com.br/polimento/boinas/boina-lustro/boina-de-espuma-preta-lustro-3-artwax",
        "marca": "Artwax",
        "fispq": null
    },
    {
        "nome": "Politriz Roto Orbital 15mm 5\" 900W/60Hz 220v + Jogo de Boinas Artwax Kit 5 Unidades",
        "descricao": "Kit Politriz Roto Orbital 15mm 5",
        "preco": "Preço não encontrado",
        "imagem": "https://images.tcdn.com.br/files/606785/themes/95/img/settings/casa.png?8d0a93ae6301f11fb3959efd9fc0d673",
        "link": "https://www.artwax.com.br/kits/kit-politriz-roto-orbital-15mm-5-900w60hz-220v-jogo-de-boinas-for-detail",
        "marca": "FOR DETAIL",
        "fispq": null
    },
    {
        "nome": "Politriz Roto Orbital 15mm 5\" 900W/60Hz 110v + Jogo de Boinas Artwax Kit  5 Unidades",
        "descricao": "Kit Politriz Roto Orbital 15mm 5",
        "preco": "Preço não encontrado",
        "imagem": "https://images.tcdn.com.br/files/606785/themes/95/img/settings/casa.png?8d0a93ae6301f11fb3959efd9fc0d673",
        "link": "https://www.artwax.com.br/kits/kit-politriz-roto-orbital-15mm-5-900w60hz-110v-jogo-de-boinas-for-detail",
        "marca": "FOR DETAIL",
        "fispq": null
    },
    {
        "nome": "Boinas de Espuma 6,5\" Corte Refino e Lustro Sem Interface Detailer Kit 3 Unidades",
        "descricao": "Kit de Boinas 6.5",
        "preco": "Preço não encontrado",
        "imagem": "https://images.tcdn.com.br/files/606785/themes/95/img/settings/casa.png?8d0a93ae6301f11fb3959efd9fc0d673",
        "link": "https://www.artwax.com.br/kit-de-boinas-de-espuma-5-5-polegadas-corte-refino-e-lustro-detailer-8273",
        "marca": "Detailer",
        "fispq": null
    },
    {
        "nome": "Boinas de Espuma 5,5\" Corte Refino e Lustro Sem Interface Detailer Kit 3 Unidades",
        "descricao": "Kit de Boinas 5.5",
        "preco": "Preço não encontrado",
        "imagem": "https://images.tcdn.com.br/files/606785/themes/95/img/settings/casa.png?8d0a93ae6301f11fb3959efd9fc0d673",
        "link": "https://www.artwax.com.br/kit-de-boinas-de-espuma-5-5-polegadas-corte-refino-e-lustro-detailer",
        "marca": "Detailer",
        "fispq": null
    },
    {
        "nome": "Kit Adaptadores Para Furadeira M14 Sigma Tools",
        "descricao": "O Kit Adaptadores Para Furadeira M14 da Sigma Tools é a solução ideal para ampliar as possibilidades da sua furadeira. Adapte suportes, escovas e outros acessórios com rosca 5/8",
        "preco": "Preço não encontrado",
        "imagem": "https://images.tcdn.com.br/files/606785/themes/95/img/settings/casa.png?8d0a93ae6301f11fb3959efd9fc0d673",
        "link": "https://www.artwax.com.br/uso-interno/kit-adaptadores-para-furadeira-m14-sigma-tools",
        "marca": "SIGMA TOOLS",
        "fispq": null
    },
    {
        "nome": "Kit Polimento Rotativa 5\" SGT-5127 2210V R&S Sigma Tools",
        "descricao": "-",
        "preco": "Preço não encontrado",
        "imagem": "https://images.tcdn.com.br/files/606785/themes/95/img/settings/casa.png?8d0a93ae6301f11fb3959efd9fc0d673",
        "link": "https://www.artwax.com.br/kit-polimento-rotativa-5-sgt-5127-2210v-r-amp-s-sigma-tools",
        "marca": "SIGMA TOOLS",
        "fispq": null
    },
    {
        "nome": "Kit Polimento Rotativa 5\" SGT-5127 110V R&S Sigma Tools",
        "descricao": "-",
        "preco": "Preço não encontrado",
        "imagem": "https://images.tcdn.com.br/files/606785/themes/95/img/settings/casa.png?8d0a93ae6301f11fb3959efd9fc0d673",
        "link": "https://www.artwax.com.br/kits/kit-polimento-rotativa-5-sgt-5127-110v-r-amp-s-sigma-tools",
        "marca": "SIGMA TOOLS",
        "fispq": null
    },
    {
        "nome": "Kit Boinas Artwax Sem Interface 3\" Corte Lustro Refino 4 Unidades",
        "descricao": "Nossa boina de espuma laranja é indicada para o uso de um corte leve ou para etapa de refino em vernizes mais duros. Produzida com espuma importada da Alemanha, sua qualidade entrega um acabamento quase sem marcas quando utilizada com o composto correto.",
        "preco": "Preço não encontrado",
        "imagem": "https://images.tcdn.com.br/files/606785/themes/95/img/settings/casa.png?8d0a93ae6301f11fb3959efd9fc0d673",
        "link": "https://www.artwax.com.br/polimento/kit-boinas-artwax-3-corte-lustro-refino-4-unidades",
        "marca": "Artwax",
        "fispq": null
    },
    {
        "nome": "Boina SDO CCS Azul Corte Sem Interface 6\" Lake Country",
        "descricao": "Patenteada em todo o mundo. Boinas SDO com tecnologia CCS. Projetada para oferecer as mesmas excelentes espumas de engenharia que a linha HDO CCS sem a construção de camada dupla.",
        "preco": "Preço não encontrado",
        "imagem": "https://images.tcdn.com.br/files/606785/themes/95/img/settings/casa.png?8d0a93ae6301f11fb3959efd9fc0d673",
        "link": "https://www.artwax.com.br/boina-sdo-ccs-azul-corte-6-lake-country",
        "marca": "Lake Country",
        "fispq": null
    },
    {
        "nome": "Boina de Lã Hibrida Corte Com Interface 5\" For Detail",
        "descricao": "Para você que precisa fazer um corte eficiente em vernizes de maior resistência, a For Detail tem a boina certa para você. Nosso modelo de lã Hibrida alia um super corte eficiente com um acabamento sem muitas marcas, economizando tempo de refino e lustro.",
        "preco": "Preço não encontrado",
        "imagem": "https://images.tcdn.com.br/files/606785/themes/95/img/settings/casa.png?8d0a93ae6301f11fb3959efd9fc0d673",
        "link": "https://www.artwax.com.br/polimento/boinas/boina-corte/boina-de-la-hibrida-5-corte-com-interface-para-politriz-rotativa-for-detail",
        "marca": "FOR DETAIL",
        "fispq": null
    },
    {
        "nome": "Boina de Espuma Laranja Refino Sem Interface 6\" For Detail",
        "descricao": "A Boina De Espuma Laranja 6? Para Refino da For Detail é a ferramenta essencial para quem busca um acabamento impecável em seu veículo. Compatível com qualquer politriz rotacional, ela é fácil de usar e oferece um excelente custo-benefício.",
        "preco": "Preço não encontrado",
        "imagem": "https://images.tcdn.com.br/files/606785/themes/95/img/settings/casa.png?8d0a93ae6301f11fb3959efd9fc0d673",
        "link": "https://www.artwax.com.br/polimento/boinas/boina-refino/boina-de-espuma-agressiva-suave-laranja-refino-6-com-furo-for-detail",
        "marca": "FOR DETAIL",
        "fispq": null
    },
    {
        "nome": "Kit Polimento Roto Orbital 21mm Giro Livre R&S SGT 5122 - 220V 900W Sigma Tools",
        "descricao": "-",
        "preco": "Preço não encontrado",
        "imagem": "https://images.tcdn.com.br/files/606785/themes/95/img/settings/casa.png?8d0a93ae6301f11fb3959efd9fc0d673",
        "link": "https://www.artwax.com.br/kit-polimento-roto-orbital-21mm-giro-livre-r-amp-s-sgt-5122-220v-900w-sigma-tools",
        "marca": "SIGMA TOOLS",
        "fispq": null
    },
    {
        "nome": "Kit Polimento Roto Orbital 21mm Giro Livre R&S SGT 5122 - 220v 900W Sigma Tools",
        "descricao": "-",
        "preco": "Preço não encontrado",
        "imagem": "https://images.tcdn.com.br/files/606785/themes/95/img/settings/casa.png?8d0a93ae6301f11fb3959efd9fc0d673",
        "link": "https://www.artwax.com.br/kits/kit-polimento-roto-orbital-21mm-900w-r-amp-s-220v-sigma-tools",
        "marca": "SIGMA TOOLS",
        "fispq": null
    },
    {
        "nome": "Boinas SDO CCS 6\" Corte Refino Lustro Lake Country Kit 3 Unidades",
        "descricao": "Patenteada em todo o mundo. Boinas SDO com tecnologia CCS. Projetada para oferecer as mesmas excelentes espumas de engenharia que a linha HDO CCS sem a construção de camada dupla.",
        "preco": "Preço não encontrado",
        "imagem": "https://images.tcdn.com.br/files/606785/themes/95/img/settings/casa.png?8d0a93ae6301f11fb3959efd9fc0d673",
        "link": "https://www.artwax.com.br/polimento/kit-de-boinas-sdo-ccs-6-polegadas-corte-refino-lustro-lake-country-3-unidades",
        "marca": "Lake Country",
        "fispq": null
    },
    {
        "nome": "Boina Jeans 3\" 75 mm Remoção de Casca de Laranja Denim Pad Carpro",
        "descricao": "A Boina Jeans Denim Pad 3? da CarPro foi especialmente projetada para remover cascas de laranja, imperfeições causadas por aplicação inadequada de tinta ou polimento.",
        "preco": "Preço não encontrado",
        "imagem": "https://images.tcdn.com.br/files/606785/themes/95/img/settings/casa.png?8d0a93ae6301f11fb3959efd9fc0d673",
        "link": "https://www.artwax.com.br/boina-jeans-3-remove-cascas-de-laranja-denim-pad-orange-peeling-carpro",
        "marca": "Carpro",
        "fispq": null
    },
    {
        "nome": "Cadillac Boina de Espuma Force Macia 6,5\" Lustro",
        "descricao": "Desenvolvidas com pequenas células e espuma ultra densa de altíssima tecnologia, a linha de boina Force, é capaz de manter os abrasivos presentes em polidores retidos a área de trabalho. Isto resulta em processo mais rápido e eficiente",
        "preco": "Preço não encontrado",
        "imagem": "https://images.tcdn.com.br/files/606785/themes/95/img/settings/casa.png?8d0a93ae6301f11fb3959efd9fc0d673",
        "link": "https://www.artwax.com.br/cadillac-boina-de-espuma-force-macia-6-5-corte",
        "marca": "Cadillac",
        "fispq": null
    },
    {
        "nome": "Boina Alumina Corte 165mm 6\" Easytech",
        "descricao": "As boinas de espuma Alumina são produzidas pela Scholl Concepts, em uma das maiores fábricas de boinas do mundo, em REMSEK.",
        "preco": "Preço não encontrado",
        "imagem": "https://images.tcdn.com.br/files/606785/themes/95/img/settings/casa.png?8d0a93ae6301f11fb3959efd9fc0d673",
        "link": "https://www.artwax.com.br/marcas/easytech/easytech-boina-alumina-corte-165mm-6",
        "marca": "Easytech",
        "fispq": null
    },
    {
        "nome": "Boina de Lã 7,5\"  Polifácil Pele Ninja Corte Pesado 321024 Lincoln Com Interface",
        "descricao": "Criada na concepção Face Unica Auto Sustentável que dispensa o uso do disco suporte para politriz. Foi desenvolvida e fabricada pela própria Lincoln,tem como características o poder de corte acentuado",
        "preco": "Preço não encontrado",
        "imagem": "https://images.tcdn.com.br/files/606785/themes/95/img/settings/casa.png?8d0a93ae6301f11fb3959efd9fc0d673",
        "link": "https://www.artwax.com.br/boina-de-la-8-polifacil-pele-ninja-corte-pesado-321024-lincoln",
        "marca": "Lincoln",
        "fispq": null
    },
    {
        "nome": "Politriz Roto Orbital 5\" Colors 15MM Azul SGT-5118 110V Sigma Tools",
        "descricao": "A Politriz Roto Orbital Colors SGT-5118 Da Sigma Tools é a ferramenta ideal para restaurar o brilho original do seu carro e um perfeito acabamento. Sua tecnologia roto orbital produz movimentos circulares e orbitais garantindo um polimento uniforme.",
        "preco": "Preço não encontrado",
        "imagem": "https://images.tcdn.com.br/files/606785/themes/95/img/settings/casa.png?8d0a93ae6301f11fb3959efd9fc0d673",
        "link": "https://www.artwax.com.br/marcas/politriz-roto-orbital-5-colors-15mm-azul-sgt-5118-110v-sigma-tools",
        "marca": "SIGMA TOOLS",
        "fispq": null
    },
    {
        "nome": "Politriz Roto Orbital 15mm 5\"  900W/60Hz For Detail - 110V",
        "descricao": "A Politriz Roto-Orbital 5",
        "preco": "Preço não encontrado",
        "imagem": "https://images.tcdn.com.br/files/606785/themes/95/img/settings/casa.png?8d0a93ae6301f11fb3959efd9fc0d673",
        "link": "https://www.artwax.com.br/maquinas-e-equipamentos/politriz-e-roto-orbital/politriz-roto-orbital-15mm-5-sgt5116-100v-900w60hz-for-detail",
        "marca": "FOR DETAIL",
        "fispq": null
    },
    {
        "nome": "Boina de lã 2\" Corte Sem Interface 320744 Lincoln",
        "descricao": "Desenvolvida sem a espuma interface para que tenha um corte ainda mais poderoso que as boinas de lã modelo SV com interface. Seu Velcro foi desenvolvido para aguentar o processo de corte em máquinas roto orbitais,",
        "preco": "Preço não encontrado",
        "imagem": "https://images.tcdn.com.br/files/606785/themes/95/img/settings/casa.png?8d0a93ae6301f11fb3959efd9fc0d673",
        "link": "https://www.artwax.com.br/boina-de-la-2-corte-pesado-sem-interface-320744-lincoln",
        "marca": "Lincoln",
        "fispq": null
    },
    {
        "nome": "Disco Interface com velcro 5\" Artwax",
        "descricao": "Conheça o Disco Interface com Velcro 5",
        "preco": "Preço não encontrado",
        "imagem": "https://images.tcdn.com.br/files/606785/themes/95/img/settings/casa.png?8d0a93ae6301f11fb3959efd9fc0d673",
        "link": "https://www.artwax.com.br/polimento/disco-interface-com-velcro-5-artwax",
        "marca": "Artwax",
        "fispq": null
    },
    {
        "nome": "Disco Interface Com Velcro 3\" Artwax",
        "descricao": "Conheça o Disco Interface com Velcro 3",
        "preco": "Preço não encontrado",
        "imagem": "https://images.tcdn.com.br/files/606785/themes/95/img/settings/casa.png?8d0a93ae6301f11fb3959efd9fc0d673",
        "link": "https://www.artwax.com.br/polimento/disco-interface-com-velcro-3-artwax",
        "marca": "Artwax",
        "fispq": null
    },
    {
        "nome": "Boinas 6\" com Furo For Detail Kit 4 Unidades",
        "descricao": "Para você que precisa fazer um corte eficiente em vernizes de maior resistência, a For Detail tem a boina certa para você.",
        "preco": "Preço não encontrado",
        "imagem": "https://images.tcdn.com.br/files/606785/themes/95/img/settings/casa.png?8d0a93ae6301f11fb3959efd9fc0d673",
        "link": "https://www.artwax.com.br/kits/kit-jogo-de-boinas-6-com-furo-for-detail",
        "marca": "FOR DETAIL",
        "fispq": null
    },
    {
        "nome": "Compressor a Bateria de Litio 18v",
        "descricao": "O Compressor alimentado com uma bateria de 18V. Através do compressor o dispositivo será pressurizado rapidamente até 2,5 bar sem esforço por parte do usuário.",
        "preco": "Preço não encontrado",
        "imagem": "https://images.tcdn.com.br/files/606785/themes/95/img/settings/casa.png?8d0a93ae6301f11fb3959efd9fc0d673",
        "link": "https://www.artwax.com.br/compressor-a-bateria-de-litio-18v",
        "marca": "IK SPRAYERS",
        "fispq": null
    }
]